{
    "54015": {
        "id": 54015,
        "type": "message",
        "date": "2023-08-08T23:35:32",
        "date_unixtime": "1691526932",
        "from": "Ізербун",
        "from_id": "user657807901",
        "reply_to_message_id": 54014,
        "text": "Азербайджанская і арабская пісьменнасць сходныя.",
        "text_entities": [
            {
                "type": "plain",
                "text": "Азербайджанская і арабская пісьменнасць сходныя."
            }
        ]
    },
    "54018": {
        "id": 54018,
        "type": "message",
        "date": "2023-08-08T23:49:24",
        "date_unixtime": "1691527764",
        "edited": "2023-08-08T23:55:39",
        "edited_unixtime": "1691528139",
        "from": "Sviatlana",
        "from_id": "user380543352",
        "reply_to_message_id": 54017,
        "text": "Як варыянт, лацінка, каб заходнікі маглі прачытаць, што за дакумент.",
        "text_entities": [
            {
                "type": "plain",
                "text": "Як варыянт, лацінка, каб заходнікі маглі прачытаць, што за дакумент."
            }
        ],
        "reactions": [
            {
                "type": "emoji",
                "count": 1,
                "emoji": "👍",
                "recent": [
                    {
                        "from": "Ізербун",
                        "from_id": "user657807901",
                        "date": "2023-08-08T23:55:40"
                    }
                ]
            }
        ]
    },
    "54042": {
        "id": 54042,
        "type": "message",
        "date": "2023-08-09T16:13:04",
        "date_unixtime": "1691586784",
        "edited": "2023-08-10T07:10:02",
        "edited_unixtime": "1691640602",
        "from": "Julia Koleda",
        "from_id": "user454470533",
        "reply_to_message_id": 54036,
        "text": "Кстати, да. Копии модно сюда, а оригиналы в школьный музей, если хранить не захочется. И..если ещё есть школа и музей. Иногда библиотеки собирают информацию при наличии заинтересованного человека.",
        "text_entities": [
            {
                "type": "plain",
                "text": "Кстати, да. Копии модно сюда, а оригиналы в школьный музей, если хранить не захочется. И..если ещё есть школа и музей. Иногда библиотеки собирают информацию при наличии заинтересованного человека."
            }
        ],
        "reactions": [
            {
                "type": "emoji",
                "count": 1,
                "emoji": "👍",
                "recent": [
                    {
                        "from": "Алена Дедясова",
                        "from_id": "user5173137076",
                        "date": "2023-08-10T07:10:02"
                    }
                ]
            }
        ]
    },
    "54103": {
        "id": 54103,
        "type": "message",
        "date": "2023-08-09T17:36:42",
        "date_unixtime": "1691591802",
        "edited": "2023-08-09T17:43:25",
        "edited_unixtime": "1691592205",
        "from": "Alenka",
        "from_id": "user1501888265",
        "reply_to_message_id": 54042,
        "text": "В библиотеках и школьных музеях, все украдут. Не нужно такое советовать людям.",
        "text_entities": [
            {
                "type": "plain",
                "text": "В библиотеках и школьных музеях, все украдут. Не нужно такое советовать людям."
            }
        ],
        "reactions": [
            {
                "type": "emoji",
                "count": 1,
                "emoji": "👍",
                "recent": [
                    {
                        "from": "В В",
                        "from_id": "user770204124",
                        "date": "2023-08-09T17:43:25"
                    }
                ]
            }
        ]
    },
    "54125": {
        "id": 54125,
        "type": "message",
        "date": "2023-08-09T23:53:31",
        "date_unixtime": "1691614411",
        "edited": "2023-08-09T23:53:45",
        "edited_unixtime": "1691614425",
        "from": "Alenka",
        "from_id": "user1501888265",
        "reply_to_message_id": 54107,
        "text": "Уносят всё, к сожалению, проверено на собственном опыте.",
        "text_entities": [
            {
                "type": "plain",
                "text": "Уносят всё, к сожалению, проверено на собственном опыте."
            }
        ],
        "reactions": [
            {
                "type": "emoji",
                "count": 1,
                "emoji": "😢",
                "recent": [
                    {
                        "from": null,
                        "from_id": "user1647115375",
                        "date": "2023-08-09T23:53:51"
                    }
                ]
            }
        ]
    },
    "54129": {
        "id": 54129,
        "type": "message",
        "date": "2023-08-10T01:01:45",
        "date_unixtime": "1691618505",
        "edited": "2023-08-10T02:17:52",
        "edited_unixtime": "1691623072",
        "from": "Ars longa Vita brevis",
        "from_id": "user662680564",
        "reply_to_message_id": 54108,
        "text": "Я адсканю ўсе докі.) Мае ўсе фота адсканеныя з архіву ўласнага і сямейнага. Ведаю, што парахнее.",
        "text_entities": [
            {
                "type": "plain",
                "text": "Я адсканю ўсе докі.) Мае ўсе фота адсканеныя з архіву ўласнага і сямейнага. Ведаю, што парахнее."
            }
        ],
        "reactions": [
            {
                "type": "emoji",
                "count": 1,
                "emoji": "👍",
                "recent": [
                    {
                        "from": "Чысты Гуманітарый",
                        "from_id": "user453928472",
                        "date": "2023-08-10T02:17:52"
                    }
                ]
            }
        ]
    },
    "54203": {
        "id": 54203,
        "type": "message",
        "date": "2023-08-10T22:22:08",
        "date_unixtime": "1691695328",
        "edited": "2023-08-10T22:26:24",
        "edited_unixtime": "1691695584",
        "from": "Vital'",
        "from_id": "user292953215",
        "reply_to_message_id": 54202,
        "text": "В мае и 1 июня 2023 г. оплачивал myheritage. Возможно мне повезло :) К PayPal очень просто привязать карту и нету лишних расходов, почему бы не протестировать свою карту. С Pyypl много на конверсии и комиссии уходит и не всеми картами USDT купишь :(",
        "text_entities": [
            {
                "type": "plain",
                "text": "В мае и 1 июня 2023 г. оплачивал myheritage. Возможно мне повезло :) К PayPal очень просто привязать карту и нету лишних расходов, почему бы не протестировать свою карту. С Pyypl много на конверсии и комиссии уходит и не всеми картами USDT купишь :("
            }
        ],
        "reactions": [
            {
                "type": "emoji",
                "count": 1,
                "emoji": "✍",
                "recent": [
                    {
                        "from": "Audoсcia",
                        "from_id": "user1846341469",
                        "date": "2023-08-10T22:22:59"
                    }
                ]
            }
        ]
    },
    "54221": {
        "id": 54221,
        "type": "message",
        "date": "2023-08-11T09:43:12",
        "date_unixtime": "1691736192",
        "from": "🤫🏍⛺",
        "from_id": "user6213882374",
        "reply_to_message_id": 54219,
        "text": "У мяне запісе пра смерць -- узрост 7 дзён, а на самой справе 4 ці 5... так гэта пра дні на пальцах адной рукі... а пра гады....",
        "text_entities": [
            {
                "type": "plain",
                "text": "У мяне запісе пра смерць -- узрост 7 дзён, а на самой справе 4 ці 5... так гэта пра дні на пальцах адной рукі... а пра гады...."
            }
        ]
    },
    "54233": {
        "id": 54233,
        "type": "message",
        "date": "2023-08-11T11:35:30",
        "date_unixtime": "1691742930",
        "from": "Алексей Арт-Хща",
        "from_id": "user207514160",
        "reply_to_message_id": 54219,
        "text": "Мапа проста, каб паказаць, што цэрквы — суседзi.",
        "text_entities": [
            {
                "type": "plain",
                "text": "Мапа проста, каб паказаць, што цэрквы — суседзi."
            }
        ]
    },
    "54235": {
        "id": 54235,
        "type": "message",
        "date": "2023-08-11T11:42:45",
        "date_unixtime": "1691743365",
        "edited": "2023-08-11T11:45:54",
        "edited_unixtime": "1691743554",
        "from": "Алексей Арт-Хща",
        "from_id": "user207514160",
        "reply_to_message_id": 54229,
        "text": "Лякарня магла i быць 🤔 Маці Мікіты памерла ў вайсковай лякарне ў мястэчку, дзе быў штаб дывізіі, да якой яны ўсе адносіліся. Але там і была пахавана. Гэта вайсковыя пасяляне. Пра заробкі, нажаль, нічога не ведаю… У Мігее царква старэйшая. Пасяляне хадзілі да яе, калі толькі пасяліліся і ў іхнем сяле царквы яшчэ не было.",
        "text_entities": [
            {
                "type": "plain",
                "text": "Лякарня магла i быць 🤔 Маці Мікіты памерла ў вайсковай лякарне ў мястэчку, дзе быў штаб дывізіі, да якой яны ўсе адносіліся. Але там і была пахавана. Гэта вайсковыя пасяляне. Пра заробкі, нажаль, нічога не ведаю… У Мігее царква старэйшая. Пасяляне хадзілі да яе, калі толькі пасяліліся і ў іхнем сяле царквы яшчэ не было."
            }
        ]
    },
    "54236": {
        "id": 54236,
        "type": "message",
        "date": "2023-08-11T11:42:52",
        "date_unixtime": "1691743372",
        "from": "Алексей Арт-Хща",
        "from_id": "user207514160",
        "reply_to_message_id": 54234,
        "text": "Так",
        "text_entities": [
            {
                "type": "plain",
                "text": "Так"
            }
        ]
    },
    "54240": {
        "id": 54240,
        "type": "message",
        "date": "2023-08-11T11:56:56",
        "date_unixtime": "1691744216",
        "edited": "2023-08-11T11:57:35",
        "edited_unixtime": "1691744255",
        "from": "Алексей Арт-Хща",
        "from_id": "user207514160",
        "reply_to_message_id": 54238,
        "text": "Там кожны месяц адзін раз на ўсех напісана, хто і дзе пахаваў. Як я разумею…",
        "text_entities": [
            {
                "type": "plain",
                "text": "Там кожны месяц адзін раз на ўсех напісана, хто і дзе пахаваў. Як я разумею…"
            }
        ],
        "reactions": [
            {
                "type": "emoji",
                "count": 1,
                "emoji": "👍",
                "recent": [
                    {
                        "from": "Audoсcia",
                        "from_id": "user1846341469",
                        "date": "2023-08-11T11:57:35"
                    }
                ]
            }
        ]
    },
    "54241": {
        "id": 54241,
        "type": "message",
        "date": "2023-08-11T11:59:30",
        "date_unixtime": "1691744370",
        "from": "Алексей Арт-Хща",
        "from_id": "user207514160",
        "reply_to_message_id": 54238,
        "text": "Таксама сустракаў. Хрышты з розніцай ў нядзелю, шлюбы… Але пахаванні ў 2 царквах сустракаю першы раз 🤷🏻‍♂️",
        "text_entities": [
            {
                "type": "plain",
                "text": "Таксама сустракаў. Хрышты з розніцай ў нядзелю, шлюбы… Але пахаванні ў 2 царквах сустракаю першы раз 🤷🏻‍♂️"
            }
        ]
    },
    "54297": {
        "id": 54297,
        "type": "message",
        "date": "2023-08-12T09:26:31",
        "date_unixtime": "1691821591",
        "edited": "2023-08-12T09:35:29",
        "edited_unixtime": "1691822129",
        "from": "Як Якуб Колас",
        "from_id": "user6256683469",
        "reply_to_message_id": 54219,
        "text": "Так, мая прапрапрабабуля за год памерла двойчы з розніцай у некалькі месяцаў.",
        "text_entities": [
            {
                "type": "plain",
                "text": "Так, мая прапрапрабабуля за год памерла двойчы з розніцай у некалькі месяцаў."
            }
        ],
        "reactions": [
            {
                "type": "emoji",
                "count": 2,
                "emoji": "🙈",
                "recent": [
                    {
                        "from": "Audoсcia",
                        "from_id": "user1846341469",
                        "date": "2023-08-12T11:13:23"
                    },
                    {
                        "from": null,
                        "from_id": "user1647115375",
                        "date": "2023-08-12T09:35:29"
                    }
                ]
            }
        ]
    },
    "54352": {
        "id": 54352,
        "type": "message",
        "date": "2023-08-12T22:33:22",
        "date_unixtime": "1691868802",
        "from": "DEN",
        "from_id": "user1702495111",
        "reply_to_message_id": 54350,
        "text": "Выдатна! Так i ёсць, на тых могiлках яны👍",
        "text_entities": [
            {
                "type": "plain",
                "text": "Выдатна! Так i ёсць, на тых могiлках яны👍"
            }
        ]
    },
    "54477": {
        "id": 54477,
        "type": "message",
        "date": "2023-08-14T13:10:14",
        "date_unixtime": "1692007814",
        "from": "🤫🏍⛺",
        "from_id": "user6213882374",
        "reply_to_message_id": 54476,
        "text": "У вордзе можна на адным файлам (яны потым самі разразаюць).",
        "text_entities": [
            {
                "type": "plain",
                "text": "У вордзе можна на адным файлам (яны потым самі разразаюць)."
            }
        ]
    },
    "54577": {
        "id": 54577,
        "type": "message",
        "date": "2023-08-14T23:35:15",
        "date_unixtime": "1692045315",
        "edited": "2023-08-14T23:59:21",
        "edited_unixtime": "1692046761",
        "from": "Алексей Арт-Хща",
        "from_id": "user207514160",
        "reply_to_message_id": 54571,
        "file": "(File not included. Change data exporting settings to download.)",
        "file_name": "2023_07_18_Арцем'еў_Тэматычны_запыт.doc",
        "mime_type": "application/msword",
        "text": "Тэматычны. Але апошнiм разам зрабiлi бескаштоўна 🤷",
        "text_entities": [
            {
                "type": "plain",
                "text": "Тэматычны. Але апошнiм разам зрабiлi бескаштоўна 🤷"
            }
        ],
        "reactions": [
            {
                "type": "emoji",
                "count": 2,
                "emoji": "✍",
                "recent": [
                    {
                        "from": "AV",
                        "from_id": "user484872692",
                        "date": "2023-08-15T08:01:38"
                    },
                    {
                        "from": "Audoсcia",
                        "from_id": "user1846341469",
                        "date": "2023-08-14T23:59:21"
                    }
                ]
            }
        ]
    },
    "54837": {
        "id": 54837,
        "type": "message",
        "date": "2023-08-16T18:21:42",
        "date_unixtime": "1692199302",
        "edited": "2023-08-16T18:25:56",
        "edited_unixtime": "1692199556",
        "from": "Julia Koleda",
        "from_id": "user454470533",
        "reply_to_message_id": 54825,
        "text": "Тоже расскажу, что имею.\n\n1. Конца не вижу. Конец в конце энтузиазма или жизни.\n2.1.Есть MH. Но не заплатила, заблокировали даже комп.версию.Только б не удалили 🙏\n2.2. Год назад маме и папе на ДР распечатывала их линию (то, что было на тот момент). \n2.3. Всю историю с самого начала собираю в документ. По факту готовая \"книга\". Оставляю красным вопросы и по ходу исправляю, дополняю. Стараюсь сейчас и фото добавлять. Изначально этого не сделала, а это дополнительное время.\n2.4. Есть распечатанная версия (ещё без фоток). Но пора заменить. \n2.5. Есть отдельно сухая история чисто по метрикам. \n3.1. Пересылала самым отзывчивым семьям \"главы\" с их историями. \n3.2. Делюсь фотками семьи, если что-то удалось найти. \n3.3. В первые два года даже бумажные открытки с НГ и чем-то ещё рассылала )) Надо бы вернуть традицию. \n3.4. Стараюсь напоминать о себе тем родственникам, кого нашла. С кем-то общаются мои родители. \n3.5. На Вики дала инфу об одной деревне. И эта практика не даёт мне спокоя, надо бы продолжить. 3.6. Сделала группу в Ок и ФБ другой деревни, чтоб и там историю транслировать. \n4. Ох, главы о родителях почти нет. Есть краткая. Но поговорить с родителями на диктофон всё как-то не удается 🧐 звучит глупо.\n5. Про себя главы нет. И не буду писать )) Приложу резюме, интервью и фотку ))\n\nНе сделано:\n- не все фото отцифрованы.\n- не все документы просмотрены и обработаны. \n- ещё я люблю распечатывать фотки (и подписывать, конечно))) но с маленьким ребенком их стало значительно больше, что я закопалась и уже года 3 не распечатываю. Косяк, за который сложно взяться.\n- но и конечно, не получены ещё ответы на многие вопросы. \n\nПохоже, мой синдром самозванца добрался и сюда ))) Дел хватает, букв много, а результат неочевиден.",
        "text_entities": [
            {
                "type": "plain",
                "text": "Тоже расскажу, что имею.\n\n1. Конца не вижу. Конец в конце энтузиазма или жизни.\n2.1.Есть MH. Но не заплатила, заблокировали даже комп.версию.Только б не удалили 🙏\n2.2. Год назад маме и папе на ДР распечатывала их линию (то, что было на тот момент). \n2.3. Всю историю с самого начала собираю в документ. По факту готовая \"книга\". Оставляю красным вопросы и по ходу исправляю, дополняю. Стараюсь сейчас и фото добавлять. Изначально этого не сделала, а это дополнительное время.\n2.4. Есть распечатанная версия (ещё без фоток). Но пора заменить. \n2.5. Есть отдельно сухая история чисто по метрикам. \n3.1. Пересылала самым отзывчивым семьям \"главы\" с их историями. \n3.2. Делюсь фотками семьи, если что-то удалось найти. \n3.3. В первые два года даже бумажные открытки с НГ и чем-то ещё рассылала )) Надо бы вернуть традицию. \n3.4. Стараюсь напоминать о себе тем родственникам, кого нашла. С кем-то общаются мои родители. \n3.5. На Вики дала инфу об одной деревне. И эта практика не даёт мне спокоя, надо бы продолжить. 3.6. Сделала группу в Ок и ФБ другой деревни, чтоб и там историю транслировать. \n4. Ох, главы о родителях почти нет. Есть краткая. Но поговорить с родителями на диктофон всё как-то не удается 🧐 звучит глупо.\n5. Про себя главы нет. И не буду писать )) Приложу резюме, интервью и фотку ))\n\nНе сделано:\n- не все фото отцифрованы.\n- не все документы просмотрены и обработаны. \n- ещё я люблю распечатывать фотки (и подписывать, конечно))) но с маленьким ребенком их стало значительно больше, что я закопалась и уже года 3 не распечатываю. Косяк, за который сложно взяться.\n- но и конечно, не получены ещё ответы на многие вопросы. \n\nПохоже, мой синдром самозванца добрался и сюда ))) Дел хватает, букв много, а результат неочевиден."
            }
        ],
        "reactions": [
            {
                "type": "emoji",
                "count": 10,
                "emoji": "❤",
                "recent": [
                    {
                        "from": "I D",
                        "from_id": "user5726368881",
                        "date": "2023-08-16T22:11:05"
                    },
                    {
                        "from": "Ks Arche",
                        "from_id": "user1705348657",
                        "date": "2023-08-16T21:51:01"
                    }
                ]
            },
            {
                "type": "emoji",
                "count": 4,
                "emoji": "👍",
                "recent": [
                    {
                        "from": "Алена",
                        "from_id": "user1617817551",
                        "date": "2023-08-20T21:31:17"
                    }
                ]
            }
        ]
    },
    "54839": {
        "id": 54839,
        "type": "message",
        "date": "2023-08-16T18:42:42",
        "date_unixtime": "1692200562",
        "from": "DEN",
        "from_id": "user1702495111",
        "reply_to_message_id": 54818,
        "text": "добра!\nа яшчэ што у каго ёсць?",
        "text_entities": [
            {
                "type": "plain",
                "text": "добра!\nа яшчэ што у каго ёсць?"
            }
        ]
    },
    "55000": {
        "id": 55000,
        "type": "message",
        "date": "2023-08-17T19:34:45",
        "date_unixtime": "1692290085",
        "from": "Игнатович А. Е.",
        "from_id": "user346646662",
        "reply_to_message_id": 54992,
        "text": "Жудасна мне робіцца ад іх",
        "text_entities": [
            {
                "type": "plain",
                "text": "Жудасна мне робіцца ад іх"
            }
        ]
    },
    "55002": {
        "id": 55002,
        "type": "message",
        "date": "2023-08-17T19:41:42",
        "date_unixtime": "1692290502",
        "from": "Игнатович А. Е.",
        "from_id": "user346646662",
        "reply_to_message_id": 54994,
        "text": "Ёсць спасылка на гэты спіс?",
        "text_entities": [
            {
                "type": "plain",
                "text": "Ёсць спасылка на гэты спіс?"
            }
        ]
    },
    "55134": {
        "id": 55134,
        "type": "message",
        "date": "2023-08-20T18:34:13",
        "date_unixtime": "1692545653",
        "from": "ksenia",
        "from_id": "user805895547",
        "reply_to_message_id": 55133,
        "text": "Вроде государственные",
        "text_entities": [
            {
                "type": "plain",
                "text": "Вроде государственные"
            }
        ]
    },
    "55137": {
        "id": 55137,
        "type": "message",
        "date": "2023-08-20T18:47:09",
        "date_unixtime": "1692546429",
        "edited": "2023-08-20T18:58:55",
        "edited_unixtime": "1692547135",
        "from": "A.",
        "from_id": "user853091369",
        "reply_to_message_id": 55135,
        "text": "Так і было сказана, што спачатку знайсці па паказальніку. \nЯ заказ рабіла, ст.182-184. (знайшла ў паказальніку)\nА калі атрымала, то ўбачыла, што трэба было 181об-184. \nГэта як варыянт.",
        "text_entities": [
            {
                "type": "plain",
                "text": "Так і было сказана, што спачатку знайсці па паказальніку. \nЯ заказ рабіла, ст.182-184. (знайшла ў паказальніку)\nА калі атрымала, то ўбачыла, што трэба было 181об-184. \nГэта як варыянт."
            }
        ]
    },
    "55139": {
        "id": 55139,
        "type": "message",
        "date": "2023-08-20T19:04:42",
        "date_unixtime": "1692547482",
        "from": "A.",
        "from_id": "user853091369",
        "reply_to_message_id": 55138,
        "text": "Не, я пра \"Географический указатель к описям ф.24 оп.7, оп.12\" які ёсць на сайце НІАБГР.",
        "text_entities": [
            {
                "type": "plain",
                "text": "Не, я пра \"Географический указатель к описям ф.24 оп.7, оп.12\" які ёсць на сайце НІАБГР."
            }
        ]
    },
    "55354": {
        "id": 55354,
        "type": "message",
        "date": "2023-08-25T19:41:22",
        "date_unixtime": "1692981682",
        "from": "В В",
        "from_id": "user770204124",
        "reply_to_message_id": 55352,
        "text": "В могилеве",
        "text_entities": [
            {
                "type": "plain",
                "text": "В могилеве"
            }
        ]
    },
    "55492": {
        "id": 55492,
        "type": "message",
        "date": "2023-08-29T07:47:31",
        "date_unixtime": "1693284451",
        "edited": "2023-08-29T07:49:24",
        "edited_unixtime": "1693284564",
        "from": "Al Capone",
        "from_id": "user566081977",
        "reply_to_message_id": 55450,
        "text": "Промышленные пылеуловителив в РБ видели? Я нет, хотя в не в одном архиве был, ситуацию обеспыливанием, реставрацией испытал на своих лёгких",
        "text_entities": [
            {
                "type": "plain",
                "text": "Промышленные пылеуловителив в РБ видели? Я нет, хотя в не в одном архиве был, ситуацию обеспыливанием, реставрацией испытал на своих лёгких"
            }
        ]
    },
    "55585": {
        "id": 55585,
        "type": "message",
        "date": "2023-08-30T23:52:35",
        "date_unixtime": "1693428755",
        "from": "Boris Nikitin",
        "from_id": "user516707057",
        "reply_to_message_id": 55584,
        "photo": "(File not included. Change data exporting settings to download.)",
        "width": 720,
        "height": 1280,
        "text": "Дарэчы, ЗША 3-я па загрузкам.",
        "text_entities": [
            {
                "type": "plain",
                "text": "Дарэчы, ЗША 3-я па загрузкам."
            }
        ]
    },
    "55645": {
        "id": 55645,
        "type": "message",
        "date": "2023-09-02T13:57:07",
        "date_unixtime": "1693652227",
        "edited": "2023-09-02T13:59:29",
        "edited_unixtime": "1693652369",
        "from": "Екатерина",
        "from_id": "user5201994014",
        "reply_to_message_id": 55644,
        "text": "Может, lab - laborer, рабочий? Child - ребёнок, может быть по возрасту?",
        "text_entities": [
            {
                "type": "plain",
                "text": "Может, lab - laborer, рабочий? Child - ребёнок, может быть по возрасту?"
            }
        ],
        "reactions": [
            {
                "type": "emoji",
                "count": 2,
                "emoji": "💯",
                "recent": [
                    {
                        "from": "Hanna",
                        "from_id": "user364374706",
                        "date": "2023-09-03T21:16:17"
                    },
                    {
                        "from": "Алексей Арт-Хща",
                        "from_id": "user207514160",
                        "date": "2023-09-02T13:59:29"
                    }
                ]
            }
        ]
    },
    "55647": {
        "id": 55647,
        "type": "message",
        "date": "2023-09-02T15:29:06",
        "date_unixtime": "1693657746",
        "from": "Julia Koleda",
        "from_id": "user454470533",
        "reply_to_message_id": 55637,
        "text": "Вот пусть бы они что-то содержательное поведали :) Вдруг легенды насобирали, документы находили? )",
        "text_entities": [
            {
                "type": "plain",
                "text": "Вот пусть бы они что-то содержательное поведали :) Вдруг легенды насобирали, документы находили? )"
            }
        ]
    },
    "55661": {
        "id": 55661,
        "type": "message",
        "date": "2023-09-02T23:57:20",
        "date_unixtime": "1693688240",
        "edited": "2023-09-03T07:29:55",
        "edited_unixtime": "1693715395",
        "from": "Лена",
        "from_id": "user1918841697",
        "reply_to_message_id": 55659,
        "text": "Сундук был зарыт не один. Всё, что было надо выкопали. Посуду, например. Потому что жили в землянках и с собой утащить все было не реально. Прятали и зарывали.\nЧто-то не нашли. Например, два огромных самовара. Их скорее всего смыла большая вода. Они были зарыты не далеко от берега . Наш дом с двух сторон огибает река.\n\nЯ же уже написала, что вероятно, но не точно, это были метрики, потому что постоянно звучало слово-книги. И церковь рядом с нами. А моя мама, ее сестры и брат  не могли сказать, какие точно  книги, ибо маме было 10, когда зарывали, остальным +-2 года. То есть там  книги, которые никому  были не нужны, поэтому и не откапывали.  А ещё, элементарно-боялись Сталина и репрессий.\nДа и дедушка был председателем колхоза. Потом, бабушка с дедом остались одни, дети разъехались все в 51 году. Они и не вспоминали про книги. Но про сундук и как он выглядел, знали все в семье.\n     Да, и мы не сейчас копали. А давным-давно. В прошлом веке еще😜\n   Мы знаем, где еще  2 схрона. Тоже вещи не особо нужные. \nНо там без металлоискателя не обойтись. Отроют покажу.",
        "text_entities": [
            {
                "type": "plain",
                "text": "Сундук был зарыт не один. Всё, что было надо выкопали. Посуду, например. Потому что жили в землянках и с собой утащить все было не реально. Прятали и зарывали.\nЧто-то не нашли. Например, два огромных самовара. Их скорее всего смыла большая вода. Они были зарыты не далеко от берега . Наш дом с двух сторон огибает река.\n\nЯ же уже написала, что вероятно, но не точно, это были метрики, потому что постоянно звучало слово-книги. И церковь рядом с нами. А моя мама, ее сестры и брат  не могли сказать, какие точно  книги, ибо маме было 10, когда зарывали, остальным +-2 года. То есть там  книги, которые никому  были не нужны, поэтому и не откапывали.  А ещё, элементарно-боялись Сталина и репрессий.\nДа и дедушка был председателем колхоза. Потом, бабушка с дедом остались одни, дети разъехались все в 51 году. Они и не вспоминали про книги. Но про сундук и как он выглядел, знали все в семье.\n     Да, и мы не сейчас копали. А давным-давно. В прошлом веке еще😜\n   Мы знаем, где еще  2 схрона. Тоже вещи не особо нужные. \nНо там без металлоискателя не обойтись. Отроют покажу."
            }
        ],
        "reactions": [
            {
                "type": "emoji",
                "count": 2,
                "emoji": "👍",
                "recent": [
                    {
                        "from": null,
                        "from_id": "user1647115375",
                        "date": "2023-09-04T23:03:43"
                    },
                    {
                        "from": "Audoсcia",
                        "from_id": "user1846341469",
                        "date": "2023-09-03T07:29:55"
                    }
                ]
            }
        ]
    },
    "55699": {
        "id": 55699,
        "type": "message",
        "date": "2023-09-04T01:21:52",
        "date_unixtime": "1693779712",
        "edited": "2023-09-04T07:19:37",
        "edited_unixtime": "1693801177",
        "from": "Игнатович А. Е.",
        "from_id": "user346646662",
        "reply_to_message_id": 55690,
        "text": "Палын, Чарнобыльнік",
        "text_entities": [
            {
                "type": "plain",
                "text": "Палын, Чарнобыльнік"
            }
        ],
        "reactions": [
            {
                "type": "emoji",
                "count": 1,
                "emoji": "👍",
                "recent": [
                    {
                        "from": "Bel tur Bel tur",
                        "from_id": "user1486971738",
                        "date": "2023-09-04T07:19:38"
                    }
                ]
            }
        ]
    },
    "55701": {
        "id": 55701,
        "type": "message",
        "date": "2023-09-04T08:00:24",
        "date_unixtime": "1693803624",
        "edited": "2023-09-04T08:39:53",
        "edited_unixtime": "1693805993",
        "from": "Bel tur Bel tur",
        "from_id": "user1486971738",
        "reply_to_message_id": 55699,
        "text": "А чаму палын? Дужа выразная для фатаздымка? На думку, у ёй няма нейкага сакральнама сэнсу на момант фiксавання на картку. Проста яна выразная i адметная.",
        "text_entities": [
            {
                "type": "plain",
                "text": "А чаму палын? Дужа выразная для фатаздымка? На думку, у ёй няма нейкага сакральнама сэнсу на момант фiксавання на картку. Проста яна выразная i адметная."
            }
        ],
        "reactions": [
            {
                "type": "emoji",
                "count": 1,
                "emoji": "👍",
                "recent": [
                    {
                        "from": "Audoсcia",
                        "from_id": "user1846341469",
                        "date": "2023-09-04T08:39:53"
                    }
                ]
            }
        ]
    },
    "55754": {
        "id": 55754,
        "type": "message",
        "date": "2023-09-05T15:07:04",
        "date_unixtime": "1693915624",
        "from": "Богдан Поздняк",
        "from_id": "user5685181789",
        "reply_to_message_id": 55752,
        "text": "Нет моего окончания фамилии, у меня фамилия заканчивалась на як и Дана была в честь фольварка, мне просто кажется что моим дали после отмены крепостного права, так как фольварк же не мог стоять 200 лет на одном месте",
        "text_entities": [
            {
                "type": "plain",
                "text": "Нет моего окончания фамилии, у меня фамилия заканчивалась на як и Дана была в честь фольварка, мне просто кажется что моим дали после отмены крепостного права, так как фольварк же не мог стоять 200 лет на одном месте"
            }
        ]
    },
    "55758": {
        "id": 55758,
        "type": "message",
        "date": "2023-09-05T15:21:05",
        "date_unixtime": "1693916465",
        "edited": "2023-09-05T15:21:44",
        "edited_unixtime": "1693916504",
        "from": "Богдан Поздняк",
        "from_id": "user5685181789",
        "reply_to_message_id": 55757,
        "text": "Не я это понял, спасибо. Я просто добавил что моё окончание фамилии отсутствует в статье",
        "text_entities": [
            {
                "type": "plain",
                "text": "Не я это понял, спасибо. Я просто добавил что моё окончание фамилии отсутствует в статье"
            }
        ],
        "reactions": [
            {
                "type": "emoji",
                "count": 1,
                "emoji": "👍",
                "recent": [
                    {
                        "from": "Audoсcia",
                        "from_id": "user1846341469",
                        "date": "2023-09-05T15:21:44"
                    }
                ]
            }
        ]
    },
    "55766": {
        "id": 55766,
        "type": "message",
        "date": "2023-09-05T15:35:10",
        "date_unixtime": "1693917310",
        "from": "Богдан Поздняк",
        "from_id": "user5685181789",
        "reply_to_message_id": 55761,
        "text": "Да, одного нашел, как раз с моей волости",
        "text_entities": [
            {
                "type": "plain",
                "text": "Да, одного нашел, как раз с моей волости"
            }
        ]
    },
    "55916": {
        "id": 55916,
        "type": "message",
        "date": "2023-09-07T14:38:47",
        "date_unixtime": "1694086727",
        "from": "N.Y.",
        "from_id": "user1841363435",
        "reply_to_message_id": 55915,
        "text": "Ну вось, пра што я і казаў. Кожны дырэктар у сваім архіве - як царок у сваім маленькім царстве.",
        "text_entities": [
            {
                "type": "plain",
                "text": "Ну вось, пра што я і казаў. Кожны дырэктар у сваім архіве - як царок у сваім маленькім царстве."
            }
        ]
    },
    "55919": {
        "id": 55919,
        "type": "message",
        "date": "2023-09-07T14:42:11",
        "date_unixtime": "1694086931",
        "edited": "2023-09-07T15:27:17",
        "edited_unixtime": "1694089637",
        "from": "N.Y.",
        "from_id": "user1841363435",
        "reply_to_message_id": 55917,
        "text": "Якія там грошы. Звычайная калгасная псіхалогія: лепей не даць, абы чаго не вышла.",
        "text_entities": [
            {
                "type": "plain",
                "text": "Якія там грошы. Звычайная калгасная псіхалогія: лепей не даць, абы чаго не вышла."
            }
        ],
        "reactions": [
            {
                "type": "emoji",
                "count": 3,
                "emoji": "👍",
                "recent": [
                    {
                        "from": "Надзея",
                        "from_id": "user553711532",
                        "date": "2023-09-09T15:46:17"
                    },
                    {
                        "from": "Ks Arche",
                        "from_id": "user1705348657",
                        "date": "2023-09-07T17:49:45"
                    },
                    {
                        "from": "I D",
                        "from_id": "user5726368881",
                        "date": "2023-09-07T15:27:18"
                    }
                ]
            }
        ]
    },
    "55921": {
        "id": 55921,
        "type": "message",
        "date": "2023-09-07T14:48:38",
        "date_unixtime": "1694087318",
        "edited": "2023-09-07T17:50:05",
        "edited_unixtime": "1694098205",
        "from": "N.Y.",
        "from_id": "user1841363435",
        "reply_to_message_id": 55920,
        "text": "Дзіўна. Звычайна пагаспадарчыя кнігі проста баяцца даваць. Асабліва з верасня 2021 г.",
        "text_entities": [
            {
                "type": "plain",
                "text": "Дзіўна. Звычайна пагаспадарчыя кнігі проста баяцца даваць. Асабліва з верасня 2021 г."
            }
        ],
        "reactions": [
            {
                "type": "emoji",
                "count": 1,
                "emoji": "👍",
                "recent": [
                    {
                        "from": "Ks Arche",
                        "from_id": "user1705348657",
                        "date": "2023-09-07T17:50:05"
                    }
                ]
            }
        ]
    },
    "55922": {
        "id": 55922,
        "type": "message",
        "date": "2023-09-07T14:50:38",
        "date_unixtime": "1694087438",
        "from": "N.Y.",
        "from_id": "user1841363435",
        "reply_to_message_id": 55920,
        "text": "Усё роўна гэта хутчэй форма кантролю, а не жаданне зарабіць грошай.",
        "text_entities": [
            {
                "type": "plain",
                "text": "Усё роўна гэта хутчэй форма кантролю, а не жаданне зарабіць грошай."
            }
        ]
    },
    "55925": {
        "id": 55925,
        "type": "message",
        "date": "2023-09-07T14:54:28",
        "date_unixtime": "1694087668",
        "edited": "2023-09-07T15:28:42",
        "edited_unixtime": "1694089722",
        "from": "N.Y.",
        "from_id": "user1841363435",
        "reply_to_message_id": 55924,
        "text": "Па сілавых ведамствах выйшаў паўсакрэтны цыркуляр, паводле якога павінна актывізавацца барацьба з картапалячнікамі. То бок з польскімі цэнтрамі, адмысловымі прыватнымі генеалогамі і доступам да архіўных крыніц, якія ўтрымліваюць звесткі пра \"нацыянальнасць\".",
        "text_entities": [
            {
                "type": "plain",
                "text": "Па сілавых ведамствах выйшаў паўсакрэтны цыркуляр, паводле якога павінна актывізавацца барацьба з картапалячнікамі. То бок з польскімі цэнтрамі, адмысловымі прыватнымі генеалогамі і доступам да архіўных крыніц, якія ўтрымліваюць звесткі пра \"нацыянальнасць\"."
            }
        ],
        "reactions": [
            {
                "type": "emoji",
                "count": 1,
                "emoji": "😢",
                "recent": [
                    {
                        "from": "I D",
                        "from_id": "user5726368881",
                        "date": "2023-09-07T15:28:42"
                    }
                ]
            }
        ]
    }
}